structural.v
module structural (
    input clk, rst,
    output NS_G, NS_Y, NS_R, EW_G, EW_Y, EW_R
);

    reg [1:0] state;
    reg [2:0] count;
    wire s1, s0, ns1, ns0;

    always @(posedge clk or posedge rst) begin
        if (rst) {state, count} <= 0;
        else if ((count == 4 && !state[0]) || (count == 1 && state[0])) begin
            state <= state + 1;
            count <= 0;
        end else count <= count + 1;
    end

    assign {s1, s0} = state;
    not n1(ns1, s1);
    not n0(ns0, s0);

    and g1(NS_G, ns1, ns0); 
    and g2(NS_Y, ns1, s0);  
    buf g3(NS_R, s1);       
    
    and g4(EW_G, s1, ns0);  
    and g5(EW_Y, s1, s0);   
    buf g6(EW_R, ns1);      
endmodule

dataflow.v
module dataflow (
    input clk, rst,
    output NS_G, NS_Y, NS_R, EW_G, EW_Y, EW_R
);
    reg [1:0] state;
    reg [2:0] count;
    wire tc; // Terminal Count

    assign tc = (state[1] == 0 && count == (state[0] ? 1 : 4)) || 
                (state[1] == 1 && count == (state[0] ? 1 : 4));

    always @(posedge clk or posedge rst) begin
        if (rst) begin state <= 0; count <= 0; end
        else begin
            state <= tc ? state + 1 : state;
            count <= tc ? 0 : count + 1;
        end
    end

    assign NS_G = (state == 2'b00);
    assign NS_Y = (state == 2'b01);
    assign NS_R = state[1];
    assign EW_G = (state == 2'b10);
    assign EW_Y = (state == 2'b11);
    assign EW_R = !state[1];
endmodule

behavioral.v
module behavioral (
    input clk,
    input rst,
    output reg NS_G, NS_Y, NS_R,
    output reg EW_G, EW_Y, EW_R
);
    // State Encoding
    parameter S0 = 2'b00, // NS Green, EW Red
              S1 = 2'b01, // NS Yellow, EW Red
              S2 = 2'b10, // NS Red, EW Green
              S3 = 2'b11; // NS Red, EW Yellow

    reg [1:0] state;
    reg [2:0] count;

    always @(posedge clk or posedge rst) begin
        if (rst) begin
            state <= S0;
            count <= 3'd0;
        end else begin
            case (state)
                S0: begin
                    if (count == 3'd4) begin 
                        state <= S1;
                        count <= 3'd0;
                    end else count <= count + 1;
                end
                S1: begin
                    if (count == 3'd1) begin 
                        state <= S2;
                        count <= 3'd0;
                    end else count <= count + 1;
                end
                S2: begin
                    if (count == 3'd4) begin 
                        state <= S3;
                        count <= 3'd0;
                    end else count <= count + 1;
                end
                S3: begin
                    if (count == 3'd1) begin 
                        state <= S0;
                        count <= 3'd0;
                    end else count <= count + 1;
                end
            endcase
        end
    end

    // Output Logic
    always @(*) begin
        {NS_G, NS_Y, NS_R, EW_G, EW_Y, EW_R} = 6'b000_000;
        case (state)
            S0: {NS_G, NS_R, EW_R} = 3'b101;
            S1: {NS_Y, NS_R, EW_R} = 3'b101;
            S2: {NS_R, EW_G, EW_R} = 3'b110; // NS Red, EW Green (Red is implicit)
            S3: {NS_R, EW_Y, EW_R} = 3'b110; // NS Red, EW Yellow
        endcase
        // Corrected mapping based on problem sequence:
        case (state)
            S0: {NS_G, NS_Y, NS_R, EW_G, EW_Y, EW_R} = 6'b100_001;
            S1: {NS_G, NS_Y, NS_R, EW_G, EW_Y, EW_R} = 6'b010_001;
            S2: {NS_G, NS_Y, NS_R, EW_G, EW_Y, EW_R} = 6'b001_100;
            S3: {NS_G, NS_Y, NS_R, EW_G, EW_Y, EW_R} = 6'b001_010;
        endcase
    end
endmodule

tb.v
module tb;
    reg clk, rst;

    wire b_NS_G, b_NS_Y, b_NS_R, b_EW_G, b_EW_Y, b_EW_R;
    wire d_NS_G, d_NS_Y, d_NS_R, d_EW_G, d_EW_Y, d_EW_R;
    wire s_NS_G, s_NS_Y, s_NS_R, s_EW_G, s_EW_Y, s_EW_R;

    behavioral uut_b (
        .clk(clk), .rst(rst), 
        .NS_G(b_NS_G), .NS_Y(b_NS_Y), .NS_R(b_NS_R), 
        .EW_G(b_EW_G), .EW_Y(b_EW_Y), .EW_R(b_EW_R)
    );

    dataflow uut_d (
        .clk(clk), .rst(rst), 
        .NS_G(d_NS_G), .NS_Y(d_NS_Y), .NS_R(d_NS_R), 
        .EW_G(d_EW_G), .EW_Y(d_EW_Y), .EW_R(d_EW_R)
    );

    structural uut_s (
        .clk(clk), .rst(rst), 
        .NS_G(s_NS_G), .NS_Y(s_NS_Y), .NS_R(s_NS_R), 
        .EW_G(s_EW_G), .EW_Y(s_EW_Y), .EW_R(s_EW_R)
    );

    initial begin
        clk = 0;
        forever #5 clk = ~clk;
    end

    initial begin
        $dumpfile("all_models_waveform.vcd"); 
        $dumpvars(0, tb);
        $display("Starting Traffic Light Simulation...");
        rst = 1; #15; 
        rst = 0;      
        #500;         
        $display("Simulation Complete.");
        $finish;
    end
endmodule

all_models_waveform.vcd
$date
	Fri May 01 21:49:26 2026
$end
$version
	Icarus Verilog
$end
$timescale
	1s
$end
$scope module tb $end
$var wire 1 ! s_NS_Y $end
$var wire 1 " s_NS_R $end
$var wire 1 # s_NS_G $end
$var wire 1 $ s_EW_Y $end
$var wire 1 % s_EW_R $end
$var wire 1 & s_EW_G $end
$var wire 1 ' d_NS_Y $end
$var wire 1 ( d_NS_R $end
$var wire 1 ) d_NS_G $end
$var wire 1 * d_EW_Y $end
$var wire 1 + d_EW_R $end
$var wire 1 , d_EW_G $end
$var wire 1 - b_NS_Y $end
$var wire 1 . b_NS_R $end
$var wire 1 / b_NS_G $end
$var wire 1 0 b_EW_Y $end
$var wire 1 1 b_EW_R $end
$var wire 1 2 b_EW_G $end
$var reg 1 3 clk $end
$var reg 1 4 rst $end
$scope module uut_b $end
$var wire 1 3 clk $end
$var wire 1 4 rst $end
$var reg 1 2 EW_G $end
$var reg 1 1 EW_R $end
$var reg 1 0 EW_Y $end
$var reg 1 / NS_G $end
$var reg 1 . NS_R $end
$var reg 1 - NS_Y $end
$var reg 3 5 count [2:0] $end
$var reg 2 6 state [1:0] $end
$upscope $end
$scope module uut_d $end
$var wire 1 3 clk $end
$var wire 1 4 rst $end
$var wire 1 7 tc $end
$var wire 1 ' NS_Y $end
$var wire 1 ( NS_R $end
$var wire 1 ) NS_G $end
$var wire 1 * EW_Y $end
$var wire 1 + EW_R $end
$var wire 1 , EW_G $end
$var reg 3 8 count [2:0] $end
$var reg 2 9 state [1:0] $end
$upscope $end
$scope module uut_s $end
$var wire 1 & EW_G $end
$var wire 1 % EW_R $end
$var wire 1 $ EW_Y $end
$var wire 1 # NS_G $end
$var wire 1 " NS_R $end
$var wire 1 ! NS_Y $end
$var wire 1 3 clk $end
$var wire 1 : ns0 $end
$var wire 1 ; ns1 $end
$var wire 1 4 rst $end
$var wire 1 < s1 $end
$var wire 1 = s0 $end
$var reg 3 > count [2:0] $end
$var reg 2 ? state [1:0] $end
$upscope $end
$upscope $end
$enddefinitions $end
#0
$dumpvars
b0 ?
b0 >
0=
0<
1;
1:
b0 9
b0 8
07
b0 6
b0 5
14
03
02
11
00
1/
0.
0-
0,
1+
0*
1)
0(
0'
0&
1%
0$
1#
0"
0!
$end
#5
13
#10
03
#15
b1 5
b1 8
b1 >
13
04
#20
03
#25
b10 >
b10 8
b10 5
13
#30
03
#35
b11 5
b11 8
b11 >
13
#40
03
#45
17
b100 >
b100 8
b100 5
13
#50
03
#55
0#
07
1!
0:
1-
0/
11
1=
b0 5
b1 6
b0 8
0)
1'
b1 9
b0 >
b1 ?
13
#60
03
#65
17
b1 >
b1 8
b1 5
13
#70
03
#75
0%
07
1&
1"
0;
0!
1:
1.
12
0-
01
1(
0+
1<
0=
b0 5
b10 6
b0 8
0'
1,
b10 9
b0 >
b10 ?
13
#80
03
#85
b1 >
b1 8
b1 5
13
#90
03
#95
b10 5
b10 8
b10 >
13
#100
03
#105
b11 >
b11 8
b11 5
13
#110
03
#115
17
b100 5
b100 8
b100 >
13
#120
03
#125
0&
1$
0:
07
1=
10
1.
02
b0 >
b11 ?
b0 8
0,
1*
b11 9
b0 5
b11 6
13
#130
03
#135
17
b1 5
b1 8
b1 >
13
#140
03
#145
1%
1#
0"
1;
0$
1:
07
0<
0=
0(
1+
1/
11
0.
00
b0 >
b0 ?
b0 8
1)
0*
b0 9
b0 5
b0 6
13
#150
03
#155
b1 5
b1 8
b1 >
13
#160
03
#165
b10 >
b10 8
b10 5
13
#170
03
#175
b11 5
b11 8
b11 >
13
#180
03
#185
17
b100 >
b100 8
b100 5
13
#190
03
#195
0#
07
1!
0:
1-
0/
11
1=
b0 5
b1 6
b0 8
0)
1'
b1 9
b0 >
b1 ?
13
#200
03
#205
17
b1 >
b1 8
b1 5
13
#210
03
#215
0%
07
1&
1"
0;
0!
1:
1.
12
0-
01
1(
0+
1<
0=
b0 5
b10 6
b0 8
0'
1,
b10 9
b0 >
b10 ?
13
#220
03
#225
b1 >
b1 8
b1 5
13
#230
03
#235
b10 5
b10 8
b10 >
13
#240
03
#245
b11 >
b11 8
b11 5
13
#250
03
#255
17
b100 5
b100 8
b100 >
13
#260
03
#265
0&
1$
0:
07
1=
10
1.
02
b0 >
b11 ?
b0 8
0,
1*
b11 9
b0 5
b11 6
13
#270
03
#275
17
b1 5
b1 8
b1 >
13
#280
03
#285
1%
1#
0"
1;
0$
1:
07
0<
0=
0(
1+
1/
11
0.
00
b0 >
b0 ?
b0 8
1)
0*
b0 9
b0 5
b0 6
13
#290
03
#295
b1 5
b1 8
b1 >
13
#300
03
#305
b10 >
b10 8
b10 5
13
#310
03
#315
b11 5
b11 8
b11 >
13
#320
03
#325
17
b100 >
b100 8
b100 5
13
#330
03
#335
0#
07
1!
0:
1-
0/
11
1=
b0 5
b1 6
b0 8
0)
1'
b1 9
b0 >
b1 ?
13
#340
03
#345
17
b1 >
b1 8
b1 5
13
#350
03
#355
0%
07
1&
1"
0;
0!
1:
1.
12
0-
01
1(
0+
1<
0=
b0 5
b10 6
b0 8
0'
1,
b10 9
b0 >
b10 ?
13
#360
03
#365
b1 >
b1 8
b1 5
13
#370
03
#375
b10 5
b10 8
b10 >
13
#380
03
#385
b11 >
b11 8
b11 5
13
#390
03
#395
17
b100 5
b100 8
b100 >
13
#400
03
#405
0&
1$
0:
07
1=
10
1.
02
b0 >
b11 ?
b0 8
0,
1*
b11 9
b0 5
b11 6
13
#410
03
#415
17
b1 5
b1 8
b1 >
13
#420
03
#425
1%
1#
0"
1;
0$
1:
07
0<
0=
0(
1+
1/
11
0.
00
b0 >
b0 ?
b0 8
1)
0*
b0 9
b0 5
b0 6
13
#430
03
#435
b1 5
b1 8
b1 >
13
#440
03
#445
b10 >
b10 8
b10 5
13
#450
03
#455
b11 5
b11 8
b11 >
13
#460
03
#465
17
b100 >
b100 8
b100 5
13
#470
03
#475
0#
07
1!
0:
1-
0/
11
1=
b0 5
b1 6
b0 8
0)
1'
b1 9
b0 >
b1 ?
13
#480
03
#485
17
b1 >
b1 8
b1 5
13
#490
03
#495
0%
07
1&
1"
0;
0!
1:
1.
12
0-
01
1(
0+
1<
0=
b0 5
b10 6
b0 8
0'
1,
b10 9
b0 >
b10 ?
13
#500
03
#505
b1 >
b1 8
b1 5
13
#510
03
#515
b10 5
b10 8
b10 >
13
